{"h1":"The words that contain app are listed below","h2":"A list of words that contain the letter app and can be used in any word game.","title":"Words containing app- To find any words containig with app for word game","meta":"Use this tool to find the highest scoring scrabble words containing app, where app is variable (alphabates a, b, ac, do, etc.).","wordLength":"Found 1207 words with letters containing  with a,p,p","words":[[{"word":"<strong>app</strong>ppropinquating","points":37,"i":17},{"word":"w<strong>app</strong>ppenschawings","points":37,"i":17},{"word":"<strong>app</strong>ppropinquation","points":36,"i":17},{"word":"<strong>app</strong>ppropinquities","points":36,"i":17},{"word":"<strong>app</strong>pproachability","points":35,"i":17},{"word":"mis<strong>app</strong>pprehensive","points":33,"i":17},{"word":"<strong>app</strong>pprenticeships","points":32,"i":17},{"word":"in<strong>app</strong>pplicability","points":32,"i":17},{"word":"mis<strong>app</strong>ppreciative","points":32,"i":17},{"word":"mis<strong>app</strong>pprehending","points":32,"i":17},{"word":"<strong>app</strong>pprenticehoods","points":31,"i":17},{"word":"dis<strong>app</strong>ppointingly","points":30,"i":17},{"word":"in<strong>app</strong>pprehensible","points":30,"i":17},{"word":"in<strong>app</strong>ppropriately","points":30,"i":17},{"word":"mal<strong>app</strong>ppropriated","points":30,"i":17},{"word":"mis<strong>app</strong>ppreciating","points":30,"i":17},{"word":"mis<strong>app</strong>pprehension","points":30,"i":17},{"word":"mis<strong>app</strong>ppropriated","points":30,"i":17},{"word":"over<strong>app</strong>pplication","points":30,"i":17},{"word":"un<strong>app</strong>pprehensible","points":30,"i":17},{"word":"unfl<strong>app</strong>ppableness","points":30,"i":17},{"word":"<strong>app</strong>pplicabilities","points":29,"i":17},{"word":"<strong>app</strong>pprenticements","points":29,"i":17},{"word":"dis<strong>app</strong>ppropriated","points":29,"i":17},{"word":"mal<strong>app</strong>ppropriates","points":29,"i":17},{"word":"mis<strong>app</strong>pplications","points":29,"i":17},{"word":"mis<strong>app</strong>ppreciation","points":29,"i":17},{"word":"mis<strong>app</strong>ppropriates","points":29,"i":17},{"word":"snippersn<strong>app</strong>ppers","points":29,"i":17},{"word":"<strong>app</strong>ppendicularian","points":28,"i":17},{"word":"dis<strong>app</strong>pplications","points":28,"i":17},{"word":"dis<strong>app</strong>ppointments","points":28,"i":17},{"word":"dis<strong>app</strong>pprobations","points":28,"i":17},{"word":"dis<strong>app</strong>ppropriates","points":28,"i":17},{"word":"in<strong>app</strong>pprehensions","points":28,"i":17},{"word":"re<strong>app</strong>ppropriating","points":28,"i":17},{"word":"<strong>app</strong>ppealabilities","points":27,"i":17},{"word":"<strong>app</strong>ppropriateness","points":27,"i":17},{"word":"in<strong>app</strong>ppreciations","points":27,"i":17},{"word":"re<strong>app</strong>pportionment","points":27,"i":17},{"word":"re<strong>app</strong>ppraisements","points":27,"i":17},{"word":"un<strong>app</strong>ppreciations","points":27,"i":17},{"word":"undis<strong>app</strong>ppointing","points":27,"i":17},{"word":"<strong>app</strong>ppealingnesses","points":26,"i":17},{"word":"whippersn<strong>app</strong>ppers","points":35,"i":17}],[{"word":"un<strong>app</strong>ppetizingly","points":37,"i":16},{"word":"<strong>app</strong>ppropinquated","points":36,"i":16},{"word":"w<strong>app</strong>ppenschawing","points":36,"i":16},{"word":"<strong>app</strong>ppeteezements","points":35,"i":16},{"word":"<strong>app</strong>ppropinquates","points":35,"i":16},{"word":"<strong>app</strong>ppendicectomy","points":34,"i":16},{"word":"in<strong>app</strong>pproachably","points":34,"i":16},{"word":"un<strong>app</strong>pproachably","points":34,"i":16},{"word":"w<strong>app</strong>ppenshawings","points":34,"i":16},{"word":"<strong>app</strong>pprehensively","points":33,"i":16},{"word":"<strong>app</strong>pproximations","points":33,"i":16},{"word":"<strong>app</strong>ppreciatively","points":32,"i":16},{"word":"cl<strong>app</strong>pperclawing","points":32,"i":16},{"word":"dis<strong>app</strong>pprovingly","points":32,"i":16},{"word":"unfl<strong>app</strong>ppability","points":32,"i":16},{"word":"<strong>app</strong>pprenticeship","points":31,"i":16},{"word":"cl<strong>app</strong>pperclawers","points":31,"i":16},{"word":"in<strong>app</strong>pproachable","points":31,"i":16},{"word":"mis<strong>app</strong>pprehended","points":31,"i":16},{"word":"nonhandic<strong>app</strong>pped","points":31,"i":16},{"word":"r<strong>app</strong>pprochements","points":31,"i":16},{"word":"un<strong>app</strong>pproachable","points":31,"i":16},{"word":"<strong>app</strong>pprenticehood","points":30,"i":16},{"word":"dis<strong>app</strong>pprobative","points":30,"i":16},{"word":"dis<strong>app</strong>pprobatory","points":30,"i":16},{"word":"in<strong>app</strong>pprehensive","points":30,"i":16},{"word":"un<strong>app</strong>pprehensive","points":30,"i":16},{"word":"<strong>app</strong>ppendectomies","points":29,"i":16},{"word":"<strong>app</strong>ppreciatorily","points":29,"i":16},{"word":"c<strong>app</strong>pparidaceous","points":29,"i":16},{"word":"dis<strong>app</strong>ppointedly","points":29,"i":16},{"word":"in<strong>app</strong>ppreciative","points":29,"i":16},{"word":"mis<strong>app</strong>ppreciated","points":29,"i":16},{"word":"un<strong>app</strong>ppreciative","points":29,"i":16},{"word":"<strong>app</strong>pplicableness","points":28,"i":16},{"word":"<strong>app</strong>pprenticement","points":28,"i":16},{"word":"claptr<strong>app</strong>pperies","points":28,"i":16},{"word":"mal<strong>app</strong>ppropriate","points":28,"i":16},{"word":"mis<strong>app</strong>pplication","points":28,"i":16},{"word":"mis<strong>app</strong>ppreciates","points":28,"i":16},{"word":"mis<strong>app</strong>ppropriate","points":28,"i":16},{"word":"nonoverl<strong>app</strong>pping","points":28,"i":16},{"word":"snippersn<strong>app</strong>pper","points":28,"i":16},{"word":"sub<strong>app</strong>ppearances","points":28,"i":16},{"word":"un<strong>app</strong>ppetisingly","points":28,"i":16},{"word":"<strong>app</strong>ppendicitises","points":27,"i":16},{"word":"dis<strong>app</strong>ppearances","points":27,"i":16},{"word":"dis<strong>app</strong>pplication","points":27,"i":16},{"word":"dis<strong>app</strong>ppointment","points":27,"i":16},{"word":"dis<strong>app</strong>pprobation","points":27,"i":16},{"word":"dis<strong>app</strong>ppropriate","points":27,"i":16},{"word":"in<strong>app</strong>pprehension","points":27,"i":16},{"word":"mal<strong>app</strong>pportioned","points":27,"i":16},{"word":"re<strong>app</strong>ppropriated","points":27,"i":16},{"word":"sn<strong>app</strong>ppishnesses","points":27,"i":16},{"word":"un<strong>app</strong>ppropriated","points":27,"i":16},{"word":"<strong>app</strong>ppertainances","points":26,"i":16},{"word":"<strong>app</strong>ppertainments","points":26,"i":16},{"word":"<strong>app</strong>pportionments","points":26,"i":16},{"word":"<strong>app</strong>ppropriations","points":26,"i":16},{"word":"dis<strong>app</strong>pparelling","points":26,"i":16},{"word":"in<strong>app</strong>ppreciation","points":26,"i":16},{"word":"non<strong>app</strong>ppearances","points":26,"i":16},{"word":"re<strong>app</strong>pplications","points":26,"i":16},{"word":"re<strong>app</strong>ppointments","points":26,"i":16},{"word":"re<strong>app</strong>ppraisement","points":26,"i":16},{"word":"re<strong>app</strong>ppropriates","points":26,"i":16},{"word":"un<strong>app</strong>ppreciation","points":26,"i":16},{"word":"understr<strong>app</strong>pping","points":26,"i":16},{"word":"re<strong>app</strong>pportioning","points":25,"i":16},{"word":"understr<strong>app</strong>ppers","points":25,"i":16},{"word":"<strong>app</strong>pparentnesses","points":24,"i":16},{"word":"<strong>app</strong>ppositenesses","points":24,"i":16},{"word":"in<strong>app</strong>ppositeness","points":24,"i":16},{"word":"whippersn<strong>app</strong>pper","points":34,"i":16}],[{"word":"<strong>app</strong>ppropinquity","points":37,"i":15},{"word":"<strong>app</strong>ppropinquing","points":35,"i":15},{"word":"<strong>app</strong>pproximately","points":35,"i":15},{"word":"<strong>app</strong>pproximative","points":35,"i":15},{"word":"<strong>app</strong>ppeteezement","points":34,"i":15},{"word":"<strong>app</strong>ppropinquate","points":34,"i":15},{"word":"<strong>app</strong>pproximating","points":33,"i":15},{"word":"h<strong>app</strong>ppenchances","points":33,"i":15},{"word":"<strong>app</strong>pproximation","points":32,"i":15},{"word":"<strong>app</strong>pplicatively","points":31,"i":15},{"word":"<strong>app</strong>pprehensibly","points":31,"i":15},{"word":"cl<strong>app</strong>pperclawed","points":31,"i":15},{"word":"<strong>app</strong>pplicability","points":30,"i":15},{"word":"cl<strong>app</strong>pperclawer","points":30,"i":15},{"word":"in<strong>app</strong>ppreciably","points":30,"i":15},{"word":"r<strong>app</strong>pprochement","points":30,"i":15},{"word":"un<strong>app</strong>pprovingly","points":30,"i":15},{"word":"<strong>app</strong>ppellatively","points":29,"i":15},{"word":"mis<strong>app</strong>pprehends","points":29,"i":15},{"word":"<strong>app</strong>ppealability","points":28,"i":15},{"word":"<strong>app</strong>pprehensible","points":28,"i":15},{"word":"<strong>app</strong>ppropriately","points":28,"i":15},{"word":"<strong>app</strong>ppropriative","points":28,"i":15},{"word":"cl<strong>app</strong>pperboards","points":28,"i":15},{"word":"h<strong>app</strong>ppenstances","points":28,"i":15},{"word":"un<strong>app</strong>pprehended","points":28,"i":15},{"word":"<strong>app</strong>pperceptions","points":27,"i":15},{"word":"<strong>app</strong>ppropriacies","points":27,"i":15},{"word":"in<strong>app</strong>ppreciable","points":27,"i":15},{"word":"mis<strong>app</strong>ppreciate","points":27,"i":15},{"word":"nonh<strong>app</strong>ppenings","points":27,"i":15},{"word":"sub<strong>app</strong>ppearance","points":27,"i":15},{"word":"un<strong>app</strong>ppealingly","points":27,"i":15},{"word":"<strong>app</strong>ppendiculate","points":26,"i":15},{"word":"<strong>app</strong>pprehensions","points":26,"i":15},{"word":"<strong>app</strong>ppropriating","points":26,"i":15},{"word":"bootstr<strong>app</strong>pping","points":26,"i":15},{"word":"dis<strong>app</strong>ppearance","points":26,"i":15},{"word":"mousetr<strong>app</strong>pping","points":26,"i":15},{"word":"pre<strong>app</strong>ppointing","points":26,"i":15},{"word":"un<strong>app</strong>ppreciated","points":26,"i":15},{"word":"unh<strong>app</strong>ppinesses","points":26,"i":15},{"word":"<strong>app</strong>ppertainance","points":25,"i":15},{"word":"<strong>app</strong>ppertainment","points":25,"i":15},{"word":"<strong>app</strong>ppetisements","points":25,"i":15},{"word":"<strong>app</strong>ppoggiaturas","points":25,"i":15},{"word":"<strong>app</strong>pportionable","points":25,"i":15},{"word":"<strong>app</strong>pportionment","points":25,"i":15},{"word":"<strong>app</strong>ppraisements","points":25,"i":15},{"word":"<strong>app</strong>ppreciations","points":25,"i":15},{"word":"<strong>app</strong>ppropriation","points":25,"i":15},{"word":"<strong>app</strong>ppropriators","points":25,"i":15},{"word":"<strong>app</strong>ppurtenances","points":25,"i":15},{"word":"c<strong>app</strong>ppernoities","points":25,"i":15},{"word":"contr<strong>app</strong>ppostos","points":25,"i":15},{"word":"dis<strong>app</strong>pparelled","points":25,"i":15},{"word":"dis<strong>app</strong>ppointing","points":25,"i":15},{"word":"in<strong>app</strong>ppetencies","points":25,"i":15},{"word":"in<strong>app</strong>ppropriate","points":25,"i":15},{"word":"mis<strong>app</strong>ppraisals","points":25,"i":15},{"word":"non<strong>app</strong>ppearance","points":25,"i":15},{"word":"re<strong>app</strong>ppearances","points":25,"i":15},{"word":"re<strong>app</strong>pplication","points":25,"i":15},{"word":"re<strong>app</strong>ppointment","points":25,"i":15},{"word":"re<strong>app</strong>ppropriate","points":25,"i":15},{"word":"scr<strong>app</strong>ppinesses","points":25,"i":15},{"word":"un<strong>app</strong>ppropriate","points":25,"i":15},{"word":"<strong>app</strong>ppealingness","points":24,"i":15},{"word":"re<strong>app</strong>pparelling","points":24,"i":15},{"word":"re<strong>app</strong>pportioned","points":24,"i":15},{"word":"un<strong>app</strong>pparelling","points":24,"i":15},{"word":"understr<strong>app</strong>pper","points":24,"i":15},{"word":"<strong>app</strong>ppellational","points":23,"i":15},{"word":"w<strong>app</strong>ppenshawing","points":33,"i":15}],[{"word":"<strong>app</strong>ppetizingly","points":35,"i":14},{"word":"<strong>app</strong>ppropinqued","points":34,"i":14},{"word":"<strong>app</strong>ppropinques","points":33,"i":14},{"word":"w<strong>app</strong>ppenschaws","points":33,"i":14},{"word":"<strong>app</strong>pproximated","points":32,"i":14},{"word":"h<strong>app</strong>ppenchance","points":32,"i":14},{"word":"un<strong>app</strong>ppetizing","points":32,"i":14},{"word":"<strong>app</strong>pparatchiki","points":31,"i":14},{"word":"<strong>app</strong>pparatchiks","points":31,"i":14},{"word":"<strong>app</strong>pproximates","points":31,"i":14},{"word":"backsl<strong>app</strong>pping","points":31,"i":14},{"word":"<strong>app</strong>ppendectomy","points":30,"i":14},{"word":"backsl<strong>app</strong>ppers","points":30,"i":14},{"word":"giftwr<strong>app</strong>pping","points":30,"i":14},{"word":"photom<strong>app</strong>pping","points":30,"i":14},{"word":"<strong>app</strong>ppeachments","points":29,"i":14},{"word":"<strong>app</strong>pperceptive","points":29,"i":14},{"word":"<strong>app</strong>pproachable","points":29,"i":14},{"word":"cl<strong>app</strong>pperclaws","points":29,"i":14},{"word":"claptr<strong>app</strong>ppery","points":29,"i":14},{"word":"fl<strong>app</strong>pperhoods","points":29,"i":14},{"word":"handic<strong>app</strong>pping","points":29,"i":14},{"word":"in<strong>app</strong>pplicably","points":29,"i":14},{"word":"kneec<strong>app</strong>ppings","points":29,"i":14},{"word":"<strong>app</strong>pperceiving","points":28,"i":14},{"word":"<strong>app</strong>pplausively","points":28,"i":14},{"word":"<strong>app</strong>ppositively","points":28,"i":14},{"word":"<strong>app</strong>ppraisively","points":28,"i":14},{"word":"<strong>app</strong>pprehensive","points":28,"i":14},{"word":"gladwr<strong>app</strong>pping","points":28,"i":14},{"word":"handic<strong>app</strong>ppers","points":28,"i":14},{"word":"mis<strong>app</strong>pprehend","points":28,"i":14},{"word":"mish<strong>app</strong>ppening","points":28,"i":14},{"word":"pre<strong>app</strong>pproving","points":28,"i":14},{"word":"un<strong>app</strong>pproached","points":28,"i":14},{"word":"<strong>app</strong>pplaudingly","points":27,"i":14},{"word":"<strong>app</strong>ppreciative","points":27,"i":14},{"word":"<strong>app</strong>ppreciatory","points":27,"i":14},{"word":"<strong>app</strong>pprehending","points":27,"i":14},{"word":"cl<strong>app</strong>pperboard","points":27,"i":14},{"word":"dis<strong>app</strong>pproving","points":27,"i":14},{"word":"h<strong>app</strong>ppenstance","points":27,"i":14},{"word":"slaph<strong>app</strong>ppiest","points":27,"i":14},{"word":"un<strong>app</strong>ppealably","points":27,"i":14},{"word":"un<strong>app</strong>ppeasably","points":27,"i":14},{"word":"<strong>app</strong>pperception","points":26,"i":14},{"word":"<strong>app</strong>ppercipient","points":26,"i":14},{"word":"<strong>app</strong>ppetisingly","points":26,"i":14},{"word":"<strong>app</strong>ppraisingly","points":26,"i":14},{"word":"<strong>app</strong>ppropriable","points":26,"i":14},{"word":"dis<strong>app</strong>pprovals","points":26,"i":14},{"word":"dis<strong>app</strong>pprovers","points":26,"i":14},{"word":"in<strong>app</strong>pplicable","points":26,"i":14},{"word":"livetr<strong>app</strong>pping","points":26,"i":14},{"word":"nonh<strong>app</strong>ppening","points":26,"i":14},{"word":"un<strong>app</strong>pplicable","points":26,"i":14},{"word":"<strong>app</strong>ppellatives","points":25,"i":14},{"word":"<strong>app</strong>ppendicitis","points":25,"i":14},{"word":"<strong>app</strong>ppendicular","points":25,"i":14},{"word":"<strong>app</strong>ppreciating","points":25,"i":14},{"word":"<strong>app</strong>pprehension","points":25,"i":14},{"word":"<strong>app</strong>pprenticing","points":25,"i":14},{"word":"<strong>app</strong>ppropriated","points":25,"i":14},{"word":"bootstr<strong>app</strong>pped","points":25,"i":14},{"word":"in<strong>app</strong>pparently","points":25,"i":14},{"word":"in<strong>app</strong>ppositely","points":25,"i":14},{"word":"mousetr<strong>app</strong>pped","points":25,"i":14},{"word":"pre<strong>app</strong>ppointed","points":25,"i":14},{"word":"sn<strong>app</strong>ppishness","points":25,"i":14},{"word":"un<strong>app</strong>pplausive","points":25,"i":14},{"word":"<strong>app</strong>pparelments","points":24,"i":14},{"word":"<strong>app</strong>ppartements","points":24,"i":14},{"word":"<strong>app</strong>ppeasements","points":24,"i":14},{"word":"<strong>app</strong>ppetisement","points":24,"i":14},{"word":"<strong>app</strong>pplications","points":24,"i":14},{"word":"<strong>app</strong>ppoggiatura","points":24,"i":14},{"word":"<strong>app</strong>ppoggiature","points":24,"i":14},{"word":"<strong>app</strong>ppointments","points":24,"i":14},{"word":"<strong>app</strong>ppraisement","points":24,"i":14},{"word":"<strong>app</strong>ppreciation","points":24,"i":14},{"word":"<strong>app</strong>ppreciators","points":24,"i":14},{"word":"<strong>app</strong>ppressorium","points":24,"i":14},{"word":"<strong>app</strong>pprobations","points":24,"i":14},{"word":"<strong>app</strong>ppropriates","points":24,"i":14},{"word":"<strong>app</strong>ppropriator","points":24,"i":14},{"word":"<strong>app</strong>ppurtenance","points":24,"i":14},{"word":"contr<strong>app</strong>pposto","points":24,"i":14},{"word":"dis<strong>app</strong>ppearing","points":24,"i":14},{"word":"dis<strong>app</strong>ppointed","points":24,"i":14},{"word":"in<strong>app</strong>ppeasable","points":24,"i":14},{"word":"in<strong>app</strong>ppellable","points":24,"i":14},{"word":"in<strong>app</strong>ppetences","points":24,"i":14},{"word":"mis<strong>app</strong>ppraisal","points":24,"i":14},{"word":"re<strong>app</strong>ppearance","points":24,"i":14},{"word":"str<strong>app</strong>ppadoing","points":24,"i":14},{"word":"un<strong>app</strong>ppealable","points":24,"i":14},{"word":"un<strong>app</strong>ppeasable","points":24,"i":14},{"word":"underl<strong>app</strong>pping","points":24,"i":14},{"word":"<strong>app</strong>ppertaining","points":23,"i":14},{"word":"<strong>app</strong>ppleringies","points":23,"i":14},{"word":"<strong>app</strong>pportioning","points":23,"i":14},{"word":"d<strong>app</strong>ppernesses","points":23,"i":14},{"word":"interl<strong>app</strong>pping","points":23,"i":14},{"word":"re<strong>app</strong>pparelled","points":23,"i":14},{"word":"re<strong>app</strong>ppointing","points":23,"i":14},{"word":"re<strong>app</strong>ppraising","points":23,"i":14},{"word":"un<strong>app</strong>pparelled","points":23,"i":14},{"word":"un<strong>app</strong>ppetising","points":23,"i":14},{"word":"<strong>app</strong>pparentness","points":22,"i":14},{"word":"<strong>app</strong>pparitional","points":22,"i":14},{"word":"<strong>app</strong>ppassionato","points":22,"i":14},{"word":"<strong>app</strong>ppellations","points":22,"i":14},{"word":"<strong>app</strong>ppertinents","points":22,"i":14},{"word":"<strong>app</strong>pportioners","points":22,"i":14},{"word":"<strong>app</strong>ppositeness","points":22,"i":14},{"word":"<strong>app</strong>ppositional","points":22,"i":14},{"word":"<strong>app</strong>ppurtenants","points":22,"i":14},{"word":"re<strong>app</strong>pportions","points":22,"i":14},{"word":"re<strong>app</strong>ppraisals","points":22,"i":14},{"word":"re<strong>app</strong>ppraisers","points":22,"i":14},{"word":"sn<strong>app</strong>ppinesses","points":22,"i":14},{"word":"tr<strong>app</strong>ppinesses","points":22,"i":14},{"word":"wiret<strong>app</strong>ppings","points":26,"i":14}],[{"word":"<strong>app</strong>ppropinque","points":32,"i":13},{"word":"w<strong>app</strong>ppenschaw","points":32,"i":13},{"word":"<strong>app</strong>ppliqueing","points":31,"i":13},{"word":"widech<strong>app</strong>pped","points":31,"i":13},{"word":"<strong>app</strong>pparatchik","points":30,"i":13},{"word":"<strong>app</strong>pproximate","points":30,"i":13},{"word":"backsl<strong>app</strong>pped","points":30,"i":13},{"word":"w<strong>app</strong>ppenshaws","points":30,"i":13},{"word":"backsl<strong>app</strong>pper","points":29,"i":13},{"word":"giftwr<strong>app</strong>pped","points":29,"i":13},{"word":"photom<strong>app</strong>pped","points":29,"i":13},{"word":"unfl<strong>app</strong>ppably","points":29,"i":13},{"word":"<strong>app</strong>ppeachment","points":28,"i":13},{"word":"<strong>app</strong>ppreciably","points":28,"i":13},{"word":"<strong>app</strong>ppropriacy","points":28,"i":13},{"word":"<strong>app</strong>pprovingly","points":28,"i":13},{"word":"cl<strong>app</strong>pperboys","points":28,"i":13},{"word":"cl<strong>app</strong>pperclaw","points":28,"i":13},{"word":"fl<strong>app</strong>pperhood","points":28,"i":13},{"word":"handic<strong>app</strong>pped","points":28,"i":13},{"word":"kneec<strong>app</strong>pping","points":28,"i":13},{"word":"<strong>app</strong>pperceived","points":27,"i":13},{"word":"<strong>app</strong>pplaudably","points":27,"i":13},{"word":"<strong>app</strong>pproaching","points":27,"i":13},{"word":"<strong>app</strong>ppulsively","points":27,"i":13},{"word":"beh<strong>app</strong>ppening","points":27,"i":13},{"word":"c<strong>app</strong>ppuccinos","points":27,"i":13},{"word":"gladwr<strong>app</strong>pped","points":27,"i":13},{"word":"handic<strong>app</strong>pper","points":27,"i":13},{"word":"kidn<strong>app</strong>ppings","points":27,"i":13},{"word":"mis<strong>app</strong>pplying","points":27,"i":13},{"word":"mish<strong>app</strong>ppened","points":27,"i":13},{"word":"pre<strong>app</strong>pplying","points":27,"i":13},{"word":"pre<strong>app</strong>pproved","points":27,"i":13},{"word":"prewr<strong>app</strong>pping","points":27,"i":13},{"word":"shipl<strong>app</strong>pping","points":27,"i":13},{"word":"<strong>app</strong>pperceives","points":26,"i":13},{"word":"<strong>app</strong>pplicative","points":26,"i":13},{"word":"<strong>app</strong>pplicatory","points":26,"i":13},{"word":"<strong>app</strong>pprehended","points":26,"i":13},{"word":"<strong>app</strong>pprobative","points":26,"i":13},{"word":"<strong>app</strong>pprobatory","points":26,"i":13},{"word":"<strong>app</strong>pprovances","points":26,"i":13},{"word":"c<strong>app</strong>ppernoity","points":26,"i":13},{"word":"dis<strong>app</strong>pplying","points":26,"i":13},{"word":"dis<strong>app</strong>pproved","points":26,"i":13},{"word":"in<strong>app</strong>ppetency","points":26,"i":13},{"word":"pre<strong>app</strong>pproves","points":26,"i":13},{"word":"slaph<strong>app</strong>ppier","points":26,"i":13},{"word":"unfl<strong>app</strong>ppable","points":26,"i":13},{"word":"<strong>app</strong>ppallingly","points":25,"i":13},{"word":"<strong>app</strong>ppealingly","points":25,"i":13},{"word":"<strong>app</strong>ppeasingly","points":25,"i":13},{"word":"<strong>app</strong>ppreciable","points":25,"i":13},{"word":"dis<strong>app</strong>pproval","points":25,"i":13},{"word":"dis<strong>app</strong>pprover","points":25,"i":13},{"word":"dis<strong>app</strong>pproves","points":25,"i":13},{"word":"enwr<strong>app</strong>ppings","points":25,"i":13},{"word":"livetr<strong>app</strong>pped","points":25,"i":13},{"word":"overl<strong>app</strong>pping","points":25,"i":13},{"word":"re<strong>app</strong>pproving","points":25,"i":13},{"word":"s<strong>app</strong>ppanwoods","points":25,"i":13},{"word":"un<strong>app</strong>pproving","points":25,"i":13},{"word":"<strong>app</strong>ppellative","points":24,"i":13},{"word":"<strong>app</strong>ppendicles","points":24,"i":13},{"word":"<strong>app</strong>pplaudable","points":24,"i":13},{"word":"<strong>app</strong>ppositives","points":24,"i":13},{"word":"<strong>app</strong>ppreciated","points":24,"i":13},{"word":"<strong>app</strong>pprenticed","points":24,"i":13},{"word":"<strong>app</strong>pprobating","points":24,"i":13},{"word":"cl<strong>app</strong>pperings","points":24,"i":13},{"word":"co<strong>app</strong>ppearing","points":24,"i":13},{"word":"dogn<strong>app</strong>ppings","points":24,"i":13},{"word":"h<strong>app</strong>ppinesses","points":24,"i":13},{"word":"s<strong>app</strong>pphirines","points":24,"i":13},{"word":"unh<strong>app</strong>ppiness","points":24,"i":13},{"word":"wiret<strong>app</strong>ppers","points":24,"i":13},{"word":"<strong>app</strong>pparelment","points":23,"i":13},{"word":"<strong>app</strong>pparencies","points":23,"i":13},{"word":"<strong>app</strong>ppartement","points":23,"i":13},{"word":"<strong>app</strong>ppearances","points":23,"i":13},{"word":"<strong>app</strong>ppeasement","points":23,"i":13},{"word":"<strong>app</strong>ppetencies","points":23,"i":13},{"word":"<strong>app</strong>pplesauces","points":23,"i":13},{"word":"<strong>app</strong>pplication","points":23,"i":13},{"word":"<strong>app</strong>pplicators","points":23,"i":13},{"word":"<strong>app</strong>ppointment","points":23,"i":13},{"word":"<strong>app</strong>ppraisable","points":23,"i":13},{"word":"<strong>app</strong>ppreciates","points":23,"i":13},{"word":"<strong>app</strong>ppreciator","points":23,"i":13},{"word":"<strong>app</strong>pprentices","points":23,"i":13},{"word":"<strong>app</strong>pprobation","points":23,"i":13},{"word":"<strong>app</strong>ppropriate","points":23,"i":13},{"word":"c<strong>app</strong>ppelletti","points":23,"i":13},{"word":"d<strong>app</strong>pperlings","points":23,"i":13},{"word":"dis<strong>app</strong>ppeared","points":23,"i":13},{"word":"in<strong>app</strong>ppetence","points":23,"i":13},{"word":"pre<strong>app</strong>ppoints","points":23,"i":13},{"word":"scr<strong>app</strong>ppiness","points":23,"i":13},{"word":"str<strong>app</strong>ppadoed","points":23,"i":13},{"word":"underl<strong>app</strong>pped","points":23,"i":13},{"word":"<strong>app</strong>pparelling","points":22,"i":13},{"word":"<strong>app</strong>ppertained","points":22,"i":13},{"word":"<strong>app</strong>ppledrains","points":22,"i":13},{"word":"<strong>app</strong>ppleringie","points":22,"i":13},{"word":"<strong>app</strong>pportioned","points":22,"i":13},{"word":"dis<strong>app</strong>pparels","points":22,"i":13},{"word":"dis<strong>app</strong>ppoints","points":22,"i":13},{"word":"interl<strong>app</strong>pped","points":22,"i":13},{"word":"r<strong>app</strong>ppellings","points":22,"i":13},{"word":"r<strong>app</strong>pportages","points":22,"i":13},{"word":"re<strong>app</strong>ppearing","points":22,"i":13},{"word":"re<strong>app</strong>ppointed","points":22,"i":13},{"word":"re<strong>app</strong>ppraised","points":22,"i":13},{"word":"str<strong>app</strong>ppadoes","points":22,"i":13},{"word":"un<strong>app</strong>ppealing","points":22,"i":13},{"word":"un<strong>app</strong>ppointed","points":22,"i":13},{"word":"unstr<strong>app</strong>pping","points":22,"i":13},{"word":"<strong>app</strong>pparatuses","points":21,"i":13},{"word":"<strong>app</strong>pparitions","points":21,"i":13},{"word":"<strong>app</strong>ppellation","points":21,"i":13},{"word":"<strong>app</strong>ppertinent","points":21,"i":13},{"word":"<strong>app</strong>ppetitions","points":21,"i":13},{"word":"<strong>app</strong>pportioner","points":21,"i":13},{"word":"<strong>app</strong>ppositions","points":21,"i":13},{"word":"<strong>app</strong>ppressoria","points":21,"i":13},{"word":"<strong>app</strong>ppurtenant","points":21,"i":13},{"word":"n<strong>app</strong>ppinesses","points":21,"i":13},{"word":"r<strong>app</strong>pporteurs","points":21,"i":13},{"word":"re<strong>app</strong>pportion","points":21,"i":13},{"word":"re<strong>app</strong>ppraisal","points":21,"i":13},{"word":"re<strong>app</strong>ppraiser","points":21,"i":13},{"word":"re<strong>app</strong>ppraises","points":21,"i":13},{"word":"s<strong>app</strong>ppinesses","points":21,"i":13},{"word":"wiret<strong>app</strong>pping","points":25,"i":13}],[{"word":"<strong>app</strong>pplejacks","points":33,"i":12},{"word":"<strong>app</strong>ppetizing","points":30,"i":12},{"word":"<strong>app</strong>pprizings","points":30,"i":12},{"word":"<strong>app</strong>ppetizers","points":29,"i":12},{"word":"<strong>app</strong>pproximal","points":29,"i":12},{"word":"w<strong>app</strong>ppenshaw","points":29,"i":12},{"word":"<strong>app</strong>ppendixes","points":28,"i":12},{"word":"<strong>app</strong>pprovably","points":28,"i":12},{"word":"affr<strong>app</strong>pping","points":27,"i":12},{"word":"<strong>app</strong>pplicably","points":27,"i":12},{"word":"cl<strong>app</strong>pperboy","points":27,"i":12},{"word":"kneec<strong>app</strong>pped","points":27,"i":12},{"word":"unh<strong>app</strong>ppying","points":27,"i":12},{"word":"<strong>app</strong>ppeaching","points":26,"i":12},{"word":"<strong>app</strong>pproached","points":26,"i":12},{"word":"bake<strong>app</strong>pples","points":26,"i":12},{"word":"beh<strong>app</strong>ppened","points":26,"i":12},{"word":"bewr<strong>app</strong>pping","points":26,"i":12},{"word":"c<strong>app</strong>ppuccino","points":26,"i":12},{"word":"fl<strong>app</strong>pperish","points":26,"i":12},{"word":"kidn<strong>app</strong>pping","points":26,"i":12},{"word":"mish<strong>app</strong>pping","points":26,"i":12},{"word":"mudc<strong>app</strong>pping","points":26,"i":12},{"word":"prewr<strong>app</strong>pped","points":26,"i":12},{"word":"sch<strong>app</strong>ppeing","points":26,"i":12},{"word":"shipl<strong>app</strong>pped","points":26,"i":12},{"word":"sn<strong>app</strong>ppishly","points":26,"i":12},{"word":"snowc<strong>app</strong>pped","points":26,"i":12},{"word":"<strong>app</strong>pperceive","points":25,"i":12},{"word":"<strong>app</strong>pproaches","points":25,"i":12},{"word":"<strong>app</strong>pprovable","points":25,"i":12},{"word":"<strong>app</strong>pprovance","points":25,"i":12},{"word":"bitm<strong>app</strong>pping","points":25,"i":12},{"word":"ch<strong>app</strong>ppesses","points":25,"i":12},{"word":"kidn<strong>app</strong>ppees","points":25,"i":12},{"word":"kidn<strong>app</strong>ppers","points":25,"i":12},{"word":"m<strong>app</strong>ppemonds","points":25,"i":12},{"word":"mish<strong>app</strong>ppens","points":25,"i":12},{"word":"pre<strong>app</strong>pprove","points":25,"i":12},{"word":"schn<strong>app</strong>ppers","points":25,"i":12},{"word":"schn<strong>app</strong>ppses","points":25,"i":12},{"word":"<strong>app</strong>pplicable","points":24,"i":12},{"word":"<strong>app</strong>pprehends","points":24,"i":12},{"word":"crab<strong>app</strong>pples","points":24,"i":12},{"word":"dis<strong>app</strong>pprove","points":24,"i":12},{"word":"enwr<strong>app</strong>pping","points":24,"i":12},{"word":"h<strong>app</strong>ppenings","points":24,"i":12},{"word":"inwr<strong>app</strong>pping","points":24,"i":12},{"word":"overl<strong>app</strong>pped","points":24,"i":12},{"word":"re<strong>app</strong>pplying","points":24,"i":12},{"word":"re<strong>app</strong>pproved","points":24,"i":12},{"word":"rec<strong>app</strong>ppable","points":24,"i":12},{"word":"rewr<strong>app</strong>pping","points":24,"i":12},{"word":"s<strong>app</strong>ppanwood","points":24,"i":12},{"word":"sn<strong>app</strong>ppingly","points":24,"i":12},{"word":"thr<strong>app</strong>ppling","points":24,"i":12},{"word":"un<strong>app</strong>pproved","points":24,"i":12},{"word":"unwr<strong>app</strong>pping","points":24,"i":12},{"word":"wiret<strong>app</strong>pped","points":24,"i":12},{"word":"<strong>app</strong>pparently","points":23,"i":12},{"word":"<strong>app</strong>ppendices","points":23,"i":12},{"word":"<strong>app</strong>ppendicle","points":23,"i":12},{"word":"<strong>app</strong>ppetitive","points":23,"i":12},{"word":"<strong>app</strong>pplausive","points":23,"i":12},{"word":"<strong>app</strong>ppointive","points":23,"i":12},{"word":"<strong>app</strong>ppositely","points":23,"i":12},{"word":"<strong>app</strong>ppositive","points":23,"i":12},{"word":"<strong>app</strong>ppraisive","points":23,"i":12},{"word":"<strong>app</strong>pprobated","points":23,"i":12},{"word":"catn<strong>app</strong>pping","points":23,"i":12},{"word":"cl<strong>app</strong>ppering","points":23,"i":12},{"word":"co<strong>app</strong>ppeared","points":23,"i":12},{"word":"dogn<strong>app</strong>pping","points":23,"i":12},{"word":"mis<strong>app</strong>pplied","points":23,"i":12},{"word":"petn<strong>app</strong>pping","points":23,"i":12},{"word":"pre<strong>app</strong>pplied","points":23,"i":12},{"word":"re<strong>app</strong>pproves","points":23,"i":12},{"word":"ripr<strong>app</strong>pping","points":23,"i":12},{"word":"s<strong>app</strong>pphirine","points":23,"i":12},{"word":"scr<strong>app</strong>ppages","points":23,"i":12},{"word":"unh<strong>app</strong>ppiest","points":23,"i":12},{"word":"wiret<strong>app</strong>pper","points":23,"i":12},{"word":"<strong>app</strong>ppealable","points":22,"i":12},{"word":"<strong>app</strong>ppearance","points":22,"i":12},{"word":"<strong>app</strong>ppeasable","points":22,"i":12},{"word":"<strong>app</strong>ppendages","points":22,"i":12},{"word":"<strong>app</strong>ppetences","points":22,"i":12},{"word":"<strong>app</strong>pplauding","points":22,"i":12},{"word":"<strong>app</strong>pplecarts","points":22,"i":12},{"word":"<strong>app</strong>pplesauce","points":22,"i":12},{"word":"<strong>app</strong>ppliances","points":22,"i":12},{"word":"<strong>app</strong>pplicants","points":22,"i":12},{"word":"<strong>app</strong>pplicator","points":22,"i":12},{"word":"<strong>app</strong>ppreciate","points":22,"i":12},{"word":"<strong>app</strong>pprentice","points":22,"i":12},{"word":"<strong>app</strong>pprobates","points":22,"i":12},{"word":"catn<strong>app</strong>ppers","points":22,"i":12},{"word":"d<strong>app</strong>pperling","points":22,"i":12},{"word":"dis<strong>app</strong>pplied","points":22,"i":12},{"word":"dogn<strong>app</strong>ppers","points":22,"i":12},{"word":"gr<strong>app</strong>pplings","points":22,"i":12},{"word":"mis<strong>app</strong>pplies","points":22,"i":12},{"word":"petn<strong>app</strong>ppers","points":22,"i":12},{"word":"pine<strong>app</strong>pples","points":22,"i":12},{"word":"pre<strong>app</strong>pplies","points":22,"i":12},{"word":"pre<strong>app</strong>ppoint","points":22,"i":12},{"word":"s<strong>app</strong>pperment","points":22,"i":12},{"word":"scr<strong>app</strong>ppiest","points":22,"i":12},{"word":"<strong>app</strong>ppareling","points":21,"i":12},{"word":"<strong>app</strong>pparelled","points":21,"i":12},{"word":"<strong>app</strong>ppendants","points":21,"i":12},{"word":"<strong>app</strong>ppendents","points":21,"i":12},{"word":"<strong>app</strong>ppetising","points":21,"i":12},{"word":"<strong>app</strong>pplauders","points":21,"i":12},{"word":"<strong>app</strong>ppledrain","points":21,"i":12},{"word":"<strong>app</strong>ppointing","points":21,"i":12},{"word":"<strong>app</strong>ppraising","points":21,"i":12},{"word":"<strong>app</strong>ppressing","points":21,"i":12},{"word":"<strong>app</strong>pprisings","points":21,"i":12},{"word":"attr<strong>app</strong>pping","points":21,"i":12},{"word":"d<strong>app</strong>pperness","points":21,"i":12},{"word":"dis<strong>app</strong>pparel","points":21,"i":12},{"word":"dis<strong>app</strong>ppears","points":21,"i":12},{"word":"dis<strong>app</strong>pplies","points":21,"i":12},{"word":"dis<strong>app</strong>ppoint","points":21,"i":12},{"word":"entr<strong>app</strong>pping","points":21,"i":12},{"word":"lagni<strong>app</strong>ppes","points":21,"i":12},{"word":"r<strong>app</strong>ppelling","points":21,"i":12},{"word":"r<strong>app</strong>pportage","points":21,"i":12},{"word":"re<strong>app</strong>ppeared","points":21,"i":12},{"word":"sn<strong>app</strong>ppering","points":21,"i":12},{"word":"str<strong>app</strong>ppados","points":21,"i":12},{"word":"str<strong>app</strong>ppings","points":21,"i":12},{"word":"un<strong>app</strong>ppalled","points":21,"i":12},{"word":"un<strong>app</strong>ppeased","points":21,"i":12},{"word":"un<strong>app</strong>pprised","points":21,"i":12},{"word":"unsn<strong>app</strong>pping","points":21,"i":12},{"word":"unstr<strong>app</strong>pped","points":21,"i":12},{"word":"<strong>app</strong>ppaloosas","points":20,"i":12},{"word":"<strong>app</strong>pparition","points":20,"i":12},{"word":"<strong>app</strong>pparitors","points":20,"i":12},{"word":"<strong>app</strong>ppellants","points":20,"i":12},{"word":"<strong>app</strong>ppertains","points":20,"i":12},{"word":"<strong>app</strong>ppetisers","points":20,"i":12},{"word":"<strong>app</strong>ppetition","points":20,"i":12},{"word":"<strong>app</strong>ppointees","points":20,"i":12},{"word":"<strong>app</strong>ppointers","points":20,"i":12},{"word":"<strong>app</strong>ppointors","points":20,"i":12},{"word":"<strong>app</strong>pportions","points":20,"i":12},{"word":"<strong>app</strong>pposition","points":20,"i":12},{"word":"<strong>app</strong>ppraisals","points":20,"i":12},{"word":"<strong>app</strong>ppraisees","points":20,"i":12},{"word":"<strong>app</strong>ppraisers","points":20,"i":12},{"word":"entr<strong>app</strong>ppers","points":20,"i":12},{"word":"in<strong>app</strong>pparent","points":20,"i":12},{"word":"in<strong>app</strong>ppetent","points":20,"i":12},{"word":"in<strong>app</strong>pposite","points":20,"i":12},{"word":"r<strong>app</strong>pporteur","points":20,"i":12},{"word":"re<strong>app</strong>pparels","points":20,"i":12},{"word":"re<strong>app</strong>ppoints","points":20,"i":12},{"word":"re<strong>app</strong>ppraise","points":20,"i":12},{"word":"sn<strong>app</strong>ppiness","points":20,"i":12},{"word":"str<strong>app</strong>ppiest","points":20,"i":12},{"word":"tr<strong>app</strong>ppiness","points":20,"i":12},{"word":"un<strong>app</strong>pparels","points":20,"i":12},{"word":"un<strong>app</strong>pparent","points":20,"i":12},{"word":"wr<strong>app</strong>ppering","points":24,"i":12}],[{"word":"<strong>app</strong>pplejack","points":32,"i":11},{"word":"<strong>app</strong>ppetized","points":29,"i":11},{"word":"<strong>app</strong>ppliqued","points":29,"i":11},{"word":"<strong>app</strong>pprizing","points":29,"i":11},{"word":"<strong>app</strong>ppetizer","points":28,"i":11},{"word":"<strong>app</strong>ppetizes","points":28,"i":11},{"word":"<strong>app</strong>ppliques","points":28,"i":11},{"word":"<strong>app</strong>pprizers","points":28,"i":11},{"word":"overh<strong>app</strong>ppy","points":28,"i":11},{"word":"mayh<strong>app</strong>ppen","points":27,"i":11},{"word":"slaph<strong>app</strong>ppy","points":27,"i":11},{"word":"affr<strong>app</strong>pped","points":26,"i":11},{"word":"<strong>app</strong>ppeached","points":25,"i":11},{"word":"bake<strong>app</strong>pple","points":25,"i":11},{"word":"bewr<strong>app</strong>pped","points":25,"i":11},{"word":"kidn<strong>app</strong>pped","points":25,"i":11},{"word":"mish<strong>app</strong>pped","points":25,"i":11},{"word":"mudc<strong>app</strong>pped","points":25,"i":11},{"word":"unh<strong>app</strong>ppily","points":25,"i":11},{"word":"<strong>app</strong>pparency","points":24,"i":11},{"word":"<strong>app</strong>ppeaches","points":24,"i":11},{"word":"<strong>app</strong>ppetency","points":24,"i":11},{"word":"bec<strong>app</strong>pping","points":24,"i":11},{"word":"beh<strong>app</strong>ppens","points":24,"i":11},{"word":"bitm<strong>app</strong>pped","points":24,"i":11},{"word":"ch<strong>app</strong>ppatis","points":24,"i":11},{"word":"ch<strong>app</strong>ppiest","points":24,"i":11},{"word":"dewl<strong>app</strong>pped","points":24,"i":11},{"word":"fl<strong>app</strong>ppable","points":24,"i":11},{"word":"icec<strong>app</strong>pped","points":24,"i":11},{"word":"kidn<strong>app</strong>ppee","points":24,"i":11},{"word":"kidn<strong>app</strong>pper","points":24,"i":11},{"word":"kn<strong>app</strong>ppling","points":24,"i":11},{"word":"m<strong>app</strong>ppemond","points":24,"i":11},{"word":"may<strong>app</strong>pples","points":24,"i":11},{"word":"mish<strong>app</strong>ppen","points":24,"i":11},{"word":"p<strong>app</strong>ppadams","points":24,"i":11},{"word":"p<strong>app</strong>ppadoms","points":24,"i":11},{"word":"s<strong>app</strong>pphisms","points":24,"i":11},{"word":"schn<strong>app</strong>pper","points":24,"i":11},{"word":"scr<strong>app</strong>ppily","points":24,"i":11},{"word":"<strong>app</strong>pprehend","points":23,"i":11},{"word":"<strong>app</strong>pproving","points":23,"i":11},{"word":"crab<strong>app</strong>pple","points":23,"i":11},{"word":"enwr<strong>app</strong>pped","points":23,"i":11},{"word":"fl<strong>app</strong>ppings","points":23,"i":11},{"word":"h<strong>app</strong>ppening","points":23,"i":11},{"word":"inwr<strong>app</strong>pped","points":23,"i":11},{"word":"rewr<strong>app</strong>pped","points":23,"i":11},{"word":"s<strong>app</strong>pphired","points":23,"i":11},{"word":"sw<strong>app</strong>ppings","points":23,"i":11},{"word":"thr<strong>app</strong>ppled","points":23,"i":11},{"word":"unfl<strong>app</strong>pped","points":23,"i":11},{"word":"unh<strong>app</strong>ppied","points":23,"i":11},{"word":"unwr<strong>app</strong>pped","points":23,"i":11},{"word":"waldr<strong>app</strong>pps","points":23,"i":11},{"word":"w<strong>app</strong>ppering","points":23,"i":11},{"word":"wr<strong>app</strong>ppages","points":23,"i":11},{"word":"wr<strong>app</strong>ppered","points":23,"i":11},{"word":"wr<strong>app</strong>ppings","points":23,"i":11},{"word":"<strong>app</strong>pprovals","points":22,"i":11},{"word":"<strong>app</strong>pprovers","points":22,"i":11},{"word":"<strong>app</strong>ppulsive","points":22,"i":11},{"word":"catn<strong>app</strong>pped","points":22,"i":11},{"word":"cl<strong>app</strong>ppered","points":22,"i":11},{"word":"cl<strong>app</strong>ppings","points":22,"i":11},{"word":"dogn<strong>app</strong>pped","points":22,"i":11},{"word":"fl<strong>app</strong>ppiest","points":22,"i":11},{"word":"h<strong>app</strong>ppiness","points":22,"i":11},{"word":"petn<strong>app</strong>pped","points":22,"i":11},{"word":"re<strong>app</strong>pprove","points":22,"i":11},{"word":"rec<strong>app</strong>pping","points":22,"i":11},{"word":"rem<strong>app</strong>pping","points":22,"i":11},{"word":"ripr<strong>app</strong>pped","points":22,"i":11},{"word":"s<strong>app</strong>pphires","points":22,"i":11},{"word":"s<strong>app</strong>pphists","points":22,"i":11},{"word":"sc<strong>app</strong>ppling","points":22,"i":11},{"word":"scr<strong>app</strong>ppage","points":22,"i":11},{"word":"scr<strong>app</strong>pping","points":22,"i":11},{"word":"t<strong>app</strong>ppicing","points":22,"i":11},{"word":"thr<strong>app</strong>pples","points":22,"i":11},{"word":"unc<strong>app</strong>pping","points":22,"i":11},{"word":"unh<strong>app</strong>ppier","points":22,"i":11},{"word":"unh<strong>app</strong>ppies","points":22,"i":11},{"word":"<strong>app</strong>ppanaged","points":21,"i":11},{"word":"<strong>app</strong>ppendage","points":21,"i":11},{"word":"<strong>app</strong>ppending","points":21,"i":11},{"word":"<strong>app</strong>ppetence","points":21,"i":11},{"word":"<strong>app</strong>ppetible","points":21,"i":11},{"word":"<strong>app</strong>pplauded","points":21,"i":11},{"word":"<strong>app</strong>pplecart","points":21,"i":11},{"word":"<strong>app</strong>ppliable","points":21,"i":11},{"word":"<strong>app</strong>ppliance","points":21,"i":11},{"word":"<strong>app</strong>pplicant","points":21,"i":11},{"word":"<strong>app</strong>pplicate","points":21,"i":11},{"word":"<strong>app</strong>pposable","points":21,"i":11},{"word":"<strong>app</strong>pprobate","points":21,"i":11},{"word":"catn<strong>app</strong>pper","points":21,"i":11},{"word":"co<strong>app</strong>ppears","points":21,"i":11},{"word":"cr<strong>app</strong>ppiest","points":21,"i":11},{"word":"did<strong>app</strong>ppers","points":21,"i":11},{"word":"dogn<strong>app</strong>pper","points":21,"i":11},{"word":"gr<strong>app</strong>ppling","points":21,"i":11},{"word":"m<strong>app</strong>pperies","points":21,"i":11},{"word":"p<strong>app</strong>ppooses","points":21,"i":11},{"word":"petn<strong>app</strong>pper","points":21,"i":11},{"word":"pine<strong>app</strong>pple","points":21,"i":11},{"word":"scr<strong>app</strong>ppers","points":21,"i":11},{"word":"scr<strong>app</strong>ppier","points":21,"i":11},{"word":"scr<strong>app</strong>pples","points":21,"i":11},{"word":"sn<strong>app</strong>ppable","points":21,"i":11},{"word":"<strong>app</strong>ppairing","points":20,"i":11},{"word":"<strong>app</strong>ppalling","points":20,"i":11},{"word":"<strong>app</strong>ppanages","points":20,"i":11},{"word":"<strong>app</strong>ppareled","points":20,"i":11},{"word":"<strong>app</strong>ppealing","points":20,"i":11},{"word":"<strong>app</strong>ppearing","points":20,"i":11},{"word":"<strong>app</strong>ppeasing","points":20,"i":11},{"word":"<strong>app</strong>ppendant","points":20,"i":11},{"word":"<strong>app</strong>ppendent","points":20,"i":11},{"word":"<strong>app</strong>ppetised","points":20,"i":11},{"word":"<strong>app</strong>pplauder","points":20,"i":11},{"word":"<strong>app</strong>ppointed","points":20,"i":11},{"word":"<strong>app</strong>ppraised","points":20,"i":11},{"word":"<strong>app</strong>ppressed","points":20,"i":11},{"word":"<strong>app</strong>pprising","points":20,"i":11},{"word":"attr<strong>app</strong>pped","points":20,"i":11},{"word":"d<strong>app</strong>pperest","points":20,"i":11},{"word":"dis<strong>app</strong>ppear","points":20,"i":11},{"word":"entr<strong>app</strong>pped","points":20,"i":11},{"word":"gr<strong>app</strong>pplers","points":20,"i":11},{"word":"lagn<strong>app</strong>ppes","points":20,"i":11},{"word":"lagni<strong>app</strong>ppe","points":20,"i":11},{"word":"l<strong>app</strong>ppering","points":20,"i":11},{"word":"r<strong>app</strong>ppeling","points":20,"i":11},{"word":"r<strong>app</strong>ppelled","points":20,"i":11},{"word":"re<strong>app</strong>pplied","points":20,"i":11},{"word":"sn<strong>app</strong>ppered","points":20,"i":11},{"word":"sn<strong>app</strong>ppings","points":20,"i":11},{"word":"str<strong>app</strong>ppado","points":20,"i":11},{"word":"str<strong>app</strong>pping","points":20,"i":11},{"word":"tr<strong>app</strong>ppings","points":20,"i":11},{"word":"un<strong>app</strong>pplied","points":20,"i":11},{"word":"unsn<strong>app</strong>pped","points":20,"i":11},{"word":"untr<strong>app</strong>pped","points":20,"i":11},{"word":"<strong>app</strong>ppaloosa","points":19,"i":11},{"word":"<strong>app</strong>pparatus","points":19,"i":11},{"word":"<strong>app</strong>pparents","points":19,"i":11},{"word":"<strong>app</strong>pparitor","points":19,"i":11},{"word":"<strong>app</strong>ppealers","points":19,"i":11},{"word":"<strong>app</strong>ppearers","points":19,"i":11},{"word":"<strong>app</strong>ppeasers","points":19,"i":11},{"word":"<strong>app</strong>ppellant","points":19,"i":11},{"word":"<strong>app</strong>ppellate","points":19,"i":11},{"word":"<strong>app</strong>ppellees","points":19,"i":11},{"word":"<strong>app</strong>ppellors","points":19,"i":11},{"word":"<strong>app</strong>pperills","points":19,"i":11},{"word":"<strong>app</strong>ppertain","points":19,"i":11},{"word":"<strong>app</strong>ppestats","points":19,"i":11},{"word":"<strong>app</strong>ppetiser","points":19,"i":11},{"word":"<strong>app</strong>ppetises","points":19,"i":11},{"word":"<strong>app</strong>ppetites","points":19,"i":11},{"word":"<strong>app</strong>pplauses","points":19,"i":11},{"word":"<strong>app</strong>ppointee","points":19,"i":11},{"word":"<strong>app</strong>ppointer","points":19,"i":11},{"word":"<strong>app</strong>ppointor","points":19,"i":11},{"word":"<strong>app</strong>pportion","points":19,"i":11},{"word":"<strong>app</strong>ppraisal","points":19,"i":11},{"word":"<strong>app</strong>ppraisee","points":19,"i":11},{"word":"<strong>app</strong>ppraiser","points":19,"i":11},{"word":"<strong>app</strong>ppraises","points":19,"i":11},{"word":"<strong>app</strong>ppresses","points":19,"i":11},{"word":"<strong>app</strong>pprisers","points":19,"i":11},{"word":"entr<strong>app</strong>pper","points":19,"i":11},{"word":"n<strong>app</strong>ppiness","points":19,"i":11},{"word":"r<strong>app</strong>pparees","points":19,"i":11},{"word":"re<strong>app</strong>pparel","points":19,"i":11},{"word":"re<strong>app</strong>ppears","points":19,"i":11},{"word":"re<strong>app</strong>pplies","points":19,"i":11},{"word":"re<strong>app</strong>ppoint","points":19,"i":11},{"word":"s<strong>app</strong>ppiness","points":19,"i":11},{"word":"sn<strong>app</strong>ppiest","points":19,"i":11},{"word":"str<strong>app</strong>ppers","points":19,"i":11},{"word":"str<strong>app</strong>ppier","points":19,"i":11},{"word":"tr<strong>app</strong>ppiest","points":19,"i":11},{"word":"un<strong>app</strong>pparel","points":19,"i":11},{"word":"y<strong>app</strong>ppingly","points":26,"i":11}],[{"word":"<strong>app</strong>pprized","points":28,"i":10},{"word":"<strong>app</strong>ppetize","points":27,"i":10},{"word":"<strong>app</strong>pplique","points":27,"i":10},{"word":"<strong>app</strong>pprizer","points":27,"i":10},{"word":"<strong>app</strong>pprizes","points":27,"i":10},{"word":"<strong>app</strong>ppendix","points":26,"i":10},{"word":"h<strong>app</strong>ppying","points":25,"i":10},{"word":"wh<strong>app</strong>pping","points":25,"i":10},{"word":"ch<strong>app</strong>pping","points":24,"i":10},{"word":"sch<strong>app</strong>pped","points":24,"i":10},{"word":"wh<strong>app</strong>ppers","points":24,"i":10},{"word":"<strong>app</strong>pproach","points":23,"i":10},{"word":"bec<strong>app</strong>pped","points":23,"i":10},{"word":"beh<strong>app</strong>ppen","points":23,"i":10},{"word":"ch<strong>app</strong>ppals","points":23,"i":10},{"word":"ch<strong>app</strong>ppati","points":23,"i":10},{"word":"ch<strong>app</strong>ppess","points":23,"i":10},{"word":"ch<strong>app</strong>ppier","points":23,"i":10},{"word":"ch<strong>app</strong>ppies","points":23,"i":10},{"word":"ech<strong>app</strong>ppes","points":23,"i":10},{"word":"kl<strong>app</strong>pping","points":23,"i":10},{"word":"kn<strong>app</strong>pping","points":23,"i":10},{"word":"kn<strong>app</strong>ppled","points":23,"i":10},{"word":"may<strong>app</strong>pple","points":23,"i":10},{"word":"mis<strong>app</strong>pply","points":23,"i":10},{"word":"p<strong>app</strong>ppadam","points":23,"i":10},{"word":"p<strong>app</strong>ppadom","points":23,"i":10},{"word":"pre<strong>app</strong>pply","points":23,"i":10},{"word":"s<strong>app</strong>pphics","points":23,"i":10},{"word":"s<strong>app</strong>pphism","points":23,"i":10},{"word":"sch<strong>app</strong>ppes","points":23,"i":10},{"word":"schn<strong>app</strong>pps","points":23,"i":10},{"word":"<strong>app</strong>ppaying","points":22,"i":10},{"word":"<strong>app</strong>pplying","points":22,"i":10},{"word":"<strong>app</strong>pproved","points":22,"i":10},{"word":"<strong>app</strong>ppuying","points":22,"i":10},{"word":"d<strong>app</strong>pperly","points":22,"i":10},{"word":"dis<strong>app</strong>pply","points":22,"i":10},{"word":"fl<strong>app</strong>pping","points":22,"i":10},{"word":"fr<strong>app</strong>pping","points":22,"i":10},{"word":"h<strong>app</strong>ppened","points":22,"i":10},{"word":"kn<strong>app</strong>ppers","points":22,"i":10},{"word":"kn<strong>app</strong>pples","points":22,"i":10},{"word":"m<strong>app</strong>ppable","points":22,"i":10},{"word":"sw<strong>app</strong>pping","points":22,"i":10},{"word":"waldr<strong>app</strong>pp","points":22,"i":10},{"word":"w<strong>app</strong>ppered","points":22,"i":10},{"word":"wr<strong>app</strong>ppage","points":22,"i":10},{"word":"wr<strong>app</strong>pping","points":22,"i":10},{"word":"<strong>app</strong>pproofs","points":21,"i":10},{"word":"<strong>app</strong>pproval","points":21,"i":10},{"word":"<strong>app</strong>pprover","points":21,"i":10},{"word":"<strong>app</strong>pproves","points":21,"i":10},{"word":"c<strong>app</strong>ppings","points":21,"i":10},{"word":"cl<strong>app</strong>pping","points":21,"i":10},{"word":"cr<strong>app</strong>pping","points":21,"i":10},{"word":"fl<strong>app</strong>ppers","points":21,"i":10},{"word":"fl<strong>app</strong>ppier","points":21,"i":10},{"word":"fr<strong>app</strong>ppant","points":21,"i":10},{"word":"h<strong>app</strong>ppiest","points":21,"i":10},{"word":"m<strong>app</strong>ppings","points":21,"i":10},{"word":"pl<strong>app</strong>pping","points":21,"i":10},{"word":"rec<strong>app</strong>pped","points":21,"i":10},{"word":"rem<strong>app</strong>pped","points":21,"i":10},{"word":"s<strong>app</strong>pphire","points":21,"i":10},{"word":"s<strong>app</strong>pphist","points":21,"i":10},{"word":"sc<strong>app</strong>ppled","points":21,"i":10},{"word":"scr<strong>app</strong>pped","points":21,"i":10},{"word":"sn<strong>app</strong>ppily","points":21,"i":10},{"word":"sn<strong>app</strong>ppish","points":21,"i":10},{"word":"sw<strong>app</strong>ppers","points":21,"i":10},{"word":"t<strong>app</strong>ppiced","points":21,"i":10},{"word":"thr<strong>app</strong>pple","points":21,"i":10},{"word":"unc<strong>app</strong>pped","points":21,"i":10},{"word":"unm<strong>app</strong>pped","points":21,"i":10},{"word":"wr<strong>app</strong>ppers","points":21,"i":10},{"word":"y<strong>app</strong>ppiest","points":21,"i":10},{"word":"<strong>app</strong>ppended","points":20,"i":10},{"word":"cl<strong>app</strong>ppers","points":20,"i":10},{"word":"co<strong>app</strong>ppear","points":20,"i":10},{"word":"cr<strong>app</strong>ppers","points":20,"i":10},{"word":"cr<strong>app</strong>ppier","points":20,"i":10},{"word":"cr<strong>app</strong>ppies","points":20,"i":10},{"word":"d<strong>app</strong>ppling","points":20,"i":10},{"word":"did<strong>app</strong>pper","points":20,"i":10},{"word":"dr<strong>app</strong>pping","points":20,"i":10},{"word":"gr<strong>app</strong>ppled","points":20,"i":10},{"word":"m<strong>app</strong>ppists","points":20,"i":10},{"word":"p<strong>app</strong>ppiest","points":20,"i":10},{"word":"p<strong>app</strong>ppoose","points":20,"i":10},{"word":"p<strong>app</strong>ppuses","points":20,"i":10},{"word":"sc<strong>app</strong>pples","points":20,"i":10},{"word":"scr<strong>app</strong>pper","points":20,"i":10},{"word":"scr<strong>app</strong>pple","points":20,"i":10},{"word":"t<strong>app</strong>ppable","points":20,"i":10},{"word":"t<strong>app</strong>ppices","points":20,"i":10},{"word":"<strong>app</strong>ppaired","points":19,"i":10},{"word":"<strong>app</strong>ppalled","points":19,"i":10},{"word":"<strong>app</strong>ppanage","points":19,"i":10},{"word":"<strong>app</strong>ppealed","points":19,"i":10},{"word":"<strong>app</strong>ppeared","points":19,"i":10},{"word":"<strong>app</strong>ppeased","points":19,"i":10},{"word":"<strong>app</strong>pplauds","points":19,"i":10},{"word":"<strong>app</strong>pposing","points":19,"i":10},{"word":"<strong>app</strong>pprised","points":19,"i":10},{"word":"d<strong>app</strong>pperer","points":19,"i":10},{"word":"dr<strong>app</strong>ppies","points":19,"i":10},{"word":"g<strong>app</strong>ppiest","points":19,"i":10},{"word":"gen<strong>app</strong>ppes","points":19,"i":10},{"word":"gr<strong>app</strong>ppler","points":19,"i":10},{"word":"gr<strong>app</strong>pples","points":19,"i":10},{"word":"lagn<strong>app</strong>ppe","points":19,"i":10},{"word":"l<strong>app</strong>ppered","points":19,"i":10},{"word":"l<strong>app</strong>ppeted","points":19,"i":10},{"word":"l<strong>app</strong>ppings","points":19,"i":10},{"word":"r<strong>app</strong>ppeled","points":19,"i":10},{"word":"r<strong>app</strong>ppings","points":19,"i":10},{"word":"s<strong>app</strong>ppling","points":19,"i":10},{"word":"sl<strong>app</strong>pping","points":19,"i":10},{"word":"sn<strong>app</strong>pping","points":19,"i":10},{"word":"st<strong>app</strong>pping","points":19,"i":10},{"word":"str<strong>app</strong>pped","points":19,"i":10},{"word":"t<strong>app</strong>ppings","points":19,"i":10},{"word":"tr<strong>app</strong>pping","points":19,"i":10},{"word":"uns<strong>app</strong>pped","points":19,"i":10},{"word":"unt<strong>app</strong>pped","points":19,"i":10},{"word":"<strong>app</strong>pparats","points":18,"i":10},{"word":"<strong>app</strong>pparels","points":18,"i":10},{"word":"<strong>app</strong>pparent","points":18,"i":10},{"word":"<strong>app</strong>ppealer","points":18,"i":10},{"word":"<strong>app</strong>ppearer","points":18,"i":10},{"word":"<strong>app</strong>ppeaser","points":18,"i":10},{"word":"<strong>app</strong>ppeases","points":18,"i":10},{"word":"<strong>app</strong>ppellee","points":18,"i":10},{"word":"<strong>app</strong>ppellor","points":18,"i":10},{"word":"<strong>app</strong>pperill","points":18,"i":10},{"word":"<strong>app</strong>pperils","points":18,"i":10},{"word":"<strong>app</strong>ppestat","points":18,"i":10},{"word":"<strong>app</strong>ppetent","points":18,"i":10},{"word":"<strong>app</strong>ppetise","points":18,"i":10},{"word":"<strong>app</strong>ppetite","points":18,"i":10},{"word":"<strong>app</strong>pplause","points":18,"i":10},{"word":"<strong>app</strong>ppliers","points":18,"i":10},{"word":"<strong>app</strong>ppoints","points":18,"i":10},{"word":"<strong>app</strong>pposers","points":18,"i":10},{"word":"<strong>app</strong>pposite","points":18,"i":10},{"word":"<strong>app</strong>ppraise","points":18,"i":10},{"word":"<strong>app</strong>ppriser","points":18,"i":10},{"word":"<strong>app</strong>pprises","points":18,"i":10},{"word":"<strong>app</strong>ppulses","points":18,"i":10},{"word":"n<strong>app</strong>ppiest","points":18,"i":10},{"word":"r<strong>app</strong>pparee","points":18,"i":10},{"word":"r<strong>app</strong>pports","points":18,"i":10},{"word":"re<strong>app</strong>ppear","points":18,"i":10},{"word":"s<strong>app</strong>ppiest","points":18,"i":10},{"word":"sl<strong>app</strong>ppers","points":18,"i":10},{"word":"sn<strong>app</strong>ppers","points":18,"i":10},{"word":"sn<strong>app</strong>ppier","points":18,"i":10},{"word":"st<strong>app</strong>pples","points":18,"i":10},{"word":"str<strong>app</strong>pper","points":18,"i":10},{"word":"tr<strong>app</strong>ppean","points":18,"i":10},{"word":"tr<strong>app</strong>ppers","points":18,"i":10},{"word":"tr<strong>app</strong>ppier","points":18,"i":10},{"word":"tr<strong>app</strong>ppose","points":18,"i":10},{"word":"tr<strong>app</strong>ppous","points":18,"i":10},{"word":"z<strong>app</strong>ppiest","points":27,"i":10}],[{"word":"<strong>app</strong>pprize","points":26,"i":9},{"word":"z<strong>app</strong>ppers","points":26,"i":9},{"word":"z<strong>app</strong>ppier","points":26,"i":9},{"word":"j<strong>app</strong>pping","points":25,"i":9},{"word":"wh<strong>app</strong>pped","points":24,"i":9},{"word":"ch<strong>app</strong>pped","points":23,"i":9},{"word":"h<strong>app</strong>ppily","points":23,"i":9},{"word":"unh<strong>app</strong>ppy","points":23,"i":9},{"word":"wh<strong>app</strong>pper","points":23,"i":9},{"word":"<strong>app</strong>ppeach","points":22,"i":9},{"word":"ch<strong>app</strong>ppal","points":22,"i":9},{"word":"ch<strong>app</strong>ppie","points":22,"i":9},{"word":"ech<strong>app</strong>ppe","points":22,"i":9},{"word":"kl<strong>app</strong>pped","points":22,"i":9},{"word":"kn<strong>app</strong>pped","points":22,"i":9},{"word":"m<strong>app</strong>ppery","points":22,"i":9},{"word":"s<strong>app</strong>pphic","points":22,"i":9},{"word":"sch<strong>app</strong>ppe","points":22,"i":9},{"word":"scr<strong>app</strong>ppy","points":22,"i":9},{"word":"<strong>app</strong>ppuyed","points":21,"i":9},{"word":"fl<strong>app</strong>pped","points":21,"i":9},{"word":"fr<strong>app</strong>pped","points":21,"i":9},{"word":"h<strong>app</strong>ppied","points":21,"i":9},{"word":"h<strong>app</strong>pping","points":21,"i":9},{"word":"kn<strong>app</strong>pper","points":21,"i":9},{"word":"kn<strong>app</strong>pple","points":21,"i":9},{"word":"sw<strong>app</strong>pped","points":21,"i":9},{"word":"w<strong>app</strong>ppend","points":21,"i":9},{"word":"w<strong>app</strong>pping","points":21,"i":9},{"word":"wr<strong>app</strong>pped","points":21,"i":9},{"word":"y<strong>app</strong>pping","points":21,"i":9},{"word":"<strong>app</strong>pproof","points":20,"i":9},{"word":"<strong>app</strong>pprove","points":20,"i":9},{"word":"c<strong>app</strong>pping","points":20,"i":9},{"word":"cl<strong>app</strong>pped","points":20,"i":9},{"word":"cr<strong>app</strong>pped","points":20,"i":9},{"word":"fl<strong>app</strong>pper","points":20,"i":9},{"word":"fr<strong>app</strong>ppee","points":20,"i":9},{"word":"fr<strong>app</strong>ppes","points":20,"i":9},{"word":"h<strong>app</strong>ppens","points":20,"i":9},{"word":"h<strong>app</strong>ppier","points":20,"i":9},{"word":"h<strong>app</strong>ppies","points":20,"i":9},{"word":"m<strong>app</strong>pping","points":20,"i":9},{"word":"p<strong>app</strong>pping","points":20,"i":9},{"word":"pl<strong>app</strong>pped","points":20,"i":9},{"word":"re<strong>app</strong>pply","points":20,"i":9},{"word":"s<strong>app</strong>ppily","points":20,"i":9},{"word":"shn<strong>app</strong>pps","points":20,"i":9},{"word":"str<strong>app</strong>ppy","points":20,"i":9},{"word":"sw<strong>app</strong>pper","points":20,"i":9},{"word":"w<strong>app</strong>ppers","points":20,"i":9},{"word":"wr<strong>app</strong>pper","points":20,"i":9},{"word":"y<strong>app</strong>ppers","points":20,"i":9},{"word":"y<strong>app</strong>ppier","points":20,"i":9},{"word":"y<strong>app</strong>ppies","points":20,"i":9},{"word":"c<strong>app</strong>ppers","points":19,"i":9},{"word":"cl<strong>app</strong>pper","points":19,"i":9},{"word":"cr<strong>app</strong>pper","points":19,"i":9},{"word":"cr<strong>app</strong>ppie","points":19,"i":9},{"word":"d<strong>app</strong>pping","points":19,"i":9},{"word":"d<strong>app</strong>ppled","points":19,"i":9},{"word":"dr<strong>app</strong>pped","points":19,"i":9},{"word":"g<strong>app</strong>pping","points":19,"i":9},{"word":"m<strong>app</strong>ppers","points":19,"i":9},{"word":"m<strong>app</strong>ppist","points":19,"i":9},{"word":"p<strong>app</strong>ppier","points":19,"i":9},{"word":"p<strong>app</strong>ppies","points":19,"i":9},{"word":"p<strong>app</strong>ppose","points":19,"i":9},{"word":"p<strong>app</strong>ppous","points":19,"i":9},{"word":"sc<strong>app</strong>pple","points":19,"i":9},{"word":"t<strong>app</strong>ppice","points":19,"i":9},{"word":"<strong>app</strong>ppends","points":18,"i":9},{"word":"<strong>app</strong>pplaud","points":18,"i":9},{"word":"<strong>app</strong>pplied","points":18,"i":9},{"word":"<strong>app</strong>pposed","points":18,"i":9},{"word":"<strong>app</strong>ppuied","points":18,"i":9},{"word":"d<strong>app</strong>ppers","points":18,"i":9},{"word":"d<strong>app</strong>pples","points":18,"i":9},{"word":"dr<strong>app</strong>ppie","points":18,"i":9},{"word":"g<strong>app</strong>ppers","points":18,"i":9},{"word":"g<strong>app</strong>ppier","points":18,"i":9},{"word":"gen<strong>app</strong>ppe","points":18,"i":9},{"word":"gr<strong>app</strong>ppas","points":18,"i":9},{"word":"gr<strong>app</strong>pple","points":18,"i":9},{"word":"l<strong>app</strong>pping","points":18,"i":9},{"word":"n<strong>app</strong>pping","points":18,"i":9},{"word":"r<strong>app</strong>pping","points":18,"i":9},{"word":"s<strong>app</strong>pping","points":18,"i":9},{"word":"s<strong>app</strong>ppled","points":18,"i":9},{"word":"sl<strong>app</strong>pped","points":18,"i":9},{"word":"sn<strong>app</strong>pped","points":18,"i":9},{"word":"st<strong>app</strong>pped","points":18,"i":9},{"word":"t<strong>app</strong>pping","points":18,"i":9},{"word":"tr<strong>app</strong>pped","points":18,"i":9},{"word":"<strong>app</strong>ppairs","points":17,"i":9},{"word":"<strong>app</strong>ppalls","points":17,"i":9},{"word":"<strong>app</strong>ppalti","points":17,"i":9},{"word":"<strong>app</strong>ppalto","points":17,"i":9},{"word":"<strong>app</strong>pparat","points":17,"i":9},{"word":"<strong>app</strong>pparel","points":17,"i":9},{"word":"<strong>app</strong>ppeals","points":17,"i":9},{"word":"<strong>app</strong>ppears","points":17,"i":9},{"word":"<strong>app</strong>ppease","points":17,"i":9},{"word":"<strong>app</strong>pperil","points":17,"i":9},{"word":"<strong>app</strong>pplets","points":17,"i":9},{"word":"<strong>app</strong>pplier","points":17,"i":9},{"word":"<strong>app</strong>pplies","points":17,"i":9},{"word":"<strong>app</strong>ppoint","points":17,"i":9},{"word":"<strong>app</strong>pports","points":17,"i":9},{"word":"<strong>app</strong>pposer","points":17,"i":9},{"word":"<strong>app</strong>pposes","points":17,"i":9},{"word":"<strong>app</strong>ppress","points":17,"i":9},{"word":"<strong>app</strong>pprise","points":17,"i":9},{"word":"<strong>app</strong>ppulse","points":17,"i":9},{"word":"l<strong>app</strong>ppels","points":17,"i":9},{"word":"l<strong>app</strong>ppers","points":17,"i":9},{"word":"l<strong>app</strong>ppets","points":17,"i":9},{"word":"l<strong>app</strong>ppies","points":17,"i":9},{"word":"n<strong>app</strong>ppers","points":17,"i":9},{"word":"n<strong>app</strong>ppier","points":17,"i":9},{"word":"n<strong>app</strong>ppies","points":17,"i":9},{"word":"r<strong>app</strong>ppees","points":17,"i":9},{"word":"r<strong>app</strong>ppels","points":17,"i":9},{"word":"r<strong>app</strong>ppers","points":17,"i":9},{"word":"r<strong>app</strong>ppini","points":17,"i":9},{"word":"r<strong>app</strong>pport","points":17,"i":9},{"word":"s<strong>app</strong>ppans","points":17,"i":9},{"word":"s<strong>app</strong>ppers","points":17,"i":9},{"word":"s<strong>app</strong>ppier","points":17,"i":9},{"word":"s<strong>app</strong>pples","points":17,"i":9},{"word":"sl<strong>app</strong>pper","points":17,"i":9},{"word":"sn<strong>app</strong>pper","points":17,"i":9},{"word":"st<strong>app</strong>pple","points":17,"i":9},{"word":"t<strong>app</strong>ppers","points":17,"i":9},{"word":"t<strong>app</strong>ppets","points":17,"i":9},{"word":"tr<strong>app</strong>pper","points":17,"i":9},{"word":"z<strong>app</strong>pping","points":27,"i":9}],[{"word":"z<strong>app</strong>pped","points":26,"i":8},{"word":"ch<strong>app</strong>ppy","points":24,"i":8},{"word":"j<strong>app</strong>pped","points":24,"i":8},{"word":"fl<strong>app</strong>ppy","points":22,"i":8},{"word":"cr<strong>app</strong>ppy","points":21,"i":8},{"word":"<strong>app</strong>ppayd","points":20,"i":8},{"word":"dr<strong>app</strong>ppy","points":20,"i":8},{"word":"h<strong>app</strong>pped","points":20,"i":8},{"word":"k<strong>app</strong>ppas","points":20,"i":8},{"word":"w<strong>app</strong>pped","points":20,"i":8},{"word":"y<strong>app</strong>pped","points":20,"i":8},{"word":"<strong>app</strong>ppays","points":19,"i":8},{"word":"<strong>app</strong>ppley","points":19,"i":8},{"word":"<strong>app</strong>ppuys","points":19,"i":8},{"word":"c<strong>app</strong>pped","points":19,"i":8},{"word":"fr<strong>app</strong>ppe","points":19,"i":8},{"word":"h<strong>app</strong>ppen","points":19,"i":8},{"word":"m<strong>app</strong>pped","points":19,"i":8},{"word":"p<strong>app</strong>pped","points":19,"i":8},{"word":"sn<strong>app</strong>ppy","points":19,"i":8},{"word":"tr<strong>app</strong>ppy","points":19,"i":8},{"word":"w<strong>app</strong>pper","points":19,"i":8},{"word":"y<strong>app</strong>pper","points":19,"i":8},{"word":"y<strong>app</strong>ppie","points":19,"i":8},{"word":"c<strong>app</strong>pper","points":18,"i":8},{"word":"d<strong>app</strong>pped","points":18,"i":8},{"word":"g<strong>app</strong>pped","points":18,"i":8},{"word":"m<strong>app</strong>pper","points":18,"i":8},{"word":"p<strong>app</strong>ppus","points":18,"i":8},{"word":"<strong>app</strong>ppaid","points":17,"i":8},{"word":"<strong>app</strong>ppend","points":17,"i":8},{"word":"d<strong>app</strong>pper","points":17,"i":8},{"word":"d<strong>app</strong>pple","points":17,"i":8},{"word":"g<strong>app</strong>pper","points":17,"i":8},{"word":"gr<strong>app</strong>ppa","points":17,"i":8},{"word":"l<strong>app</strong>pped","points":17,"i":8},{"word":"n<strong>app</strong>pped","points":17,"i":8},{"word":"r<strong>app</strong>pped","points":17,"i":8},{"word":"s<strong>app</strong>pped","points":17,"i":8},{"word":"t<strong>app</strong>pped","points":17,"i":8},{"word":"<strong>app</strong>ppair","points":16,"i":8},{"word":"<strong>app</strong>ppall","points":16,"i":8},{"word":"<strong>app</strong>ppals","points":16,"i":8},{"word":"<strong>app</strong>ppeal","points":16,"i":8},{"word":"<strong>app</strong>ppear","points":16,"i":8},{"word":"<strong>app</strong>ppels","points":16,"i":8},{"word":"<strong>app</strong>pples","points":16,"i":8},{"word":"<strong>app</strong>pplet","points":16,"i":8},{"word":"<strong>app</strong>pport","points":16,"i":8},{"word":"<strong>app</strong>ppose","points":16,"i":8},{"word":"<strong>app</strong>ppros","points":16,"i":8},{"word":"<strong>app</strong>ppuis","points":16,"i":8},{"word":"l<strong>app</strong>ppel","points":16,"i":8},{"word":"l<strong>app</strong>pper","points":16,"i":8},{"word":"l<strong>app</strong>ppet","points":16,"i":8},{"word":"l<strong>app</strong>ppie","points":16,"i":8},{"word":"n<strong>app</strong>ppas","points":16,"i":8},{"word":"n<strong>app</strong>pper","points":16,"i":8},{"word":"n<strong>app</strong>ppes","points":16,"i":8},{"word":"n<strong>app</strong>ppie","points":16,"i":8},{"word":"r<strong>app</strong>ppee","points":16,"i":8},{"word":"r<strong>app</strong>ppel","points":16,"i":8},{"word":"r<strong>app</strong>ppen","points":16,"i":8},{"word":"r<strong>app</strong>pper","points":16,"i":8},{"word":"r<strong>app</strong>ppes","points":16,"i":8},{"word":"s<strong>app</strong>ppan","points":16,"i":8},{"word":"s<strong>app</strong>pper","points":16,"i":8},{"word":"s<strong>app</strong>pple","points":16,"i":8},{"word":"t<strong>app</strong>ppas","points":16,"i":8},{"word":"t<strong>app</strong>pper","points":16,"i":8},{"word":"t<strong>app</strong>ppet","points":16,"i":8},{"word":"t<strong>app</strong>ppit","points":16,"i":8},{"word":"z<strong>app</strong>pper","points":25,"i":8}],[{"word":"h<strong>app</strong>ppy","points":21,"i":7},{"word":"y<strong>app</strong>ppy","points":21,"i":7},{"word":"p<strong>app</strong>ppy","points":20,"i":7},{"word":"g<strong>app</strong>ppy","points":19,"i":7},{"word":"k<strong>app</strong>ppa","points":19,"i":7},{"word":"<strong>app</strong>ppay","points":18,"i":7},{"word":"<strong>app</strong>pply","points":18,"i":7},{"word":"<strong>app</strong>ppuy","points":18,"i":7},{"word":"n<strong>app</strong>ppy","points":18,"i":7},{"word":"s<strong>app</strong>ppy","points":18,"i":7},{"word":"y<strong>app</strong>pps","points":18,"i":7},{"word":"p<strong>app</strong>ppi","points":17,"i":7},{"word":"<strong>app</strong>ppal","points":15,"i":7},{"word":"<strong>app</strong>ppel","points":15,"i":7},{"word":"<strong>app</strong>pple","points":15,"i":7},{"word":"<strong>app</strong>ppro","points":15,"i":7},{"word":"<strong>app</strong>ppui","points":15,"i":7},{"word":"n<strong>app</strong>ppa","points":15,"i":7},{"word":"n<strong>app</strong>ppe","points":15,"i":7},{"word":"r<strong>app</strong>ppe","points":15,"i":7},{"word":"t<strong>app</strong>ppa","points":15,"i":7},{"word":"z<strong>app</strong>ppy","points":27,"i":7}],[{"word":"<strong>app</strong>pps","points":14,"i":6},{"word":"y<strong>app</strong>pp","points":17,"i":6}],[{"word":"<strong>app</strong>pp","points":13,"i":5}]],"feature_title":"Features","blogNo":"03","blog_title":"Blog","FaqNo":"04","Faq_title":"FAQ","aboutNo":"05","about_title":"About","megaMenu":{"nav-link-name":"Tools","dropdown":[{"categoryName":"Recommended Pages","links":[{"name":"words containing meow","url":"/words-collections/words-containing-meow"},{"name":"words containing night","url":"/words-collections/words-containing-night"},{"name":"words containing gum","url":"/words-collections/words-containing-gum"},{"name":"words containing in","url":"/words-collections/words-containing-in"},{"name":"words containing ji","url":"/words-collections/words-containing-ji"},{"name":"words containing iv","url":"/words-collections/words-containing-iv"},{"name":"words containing lo","url":"/words-collections/words-containing-lo"},{"name":"words containing low","url":"/words-collections/words-containing-low"},{"name":"words containing zone","url":"/words-collections/words-containing-zone"},{"name":"words containing eli","url":"/words-collections/words-containing-eli"},{"name":"words containing qua","url":"/words-collections/words-containing-qua"},{"name":"words containing letters","url":"/words-collections/words-containing-letters"},{"name":"words containing sol","url":"/words-collections/words-containing-sol"},{"name":"words containing set","url":"/words-collections/words-containing-set"},{"name":"words containing zip","url":"/words-collections/words-containing-zip"},{"name":"words containing drive","url":"/words-collections/words-containing-drive"},{"name":"words containing loqu","url":"/words-collections/words-containing-loqu"},{"name":"words containing suq","url":"/words-collections/words-containing-suq"},{"name":"words containing teak","url":"/words-collections/words-containing-teak"},{"name":"words containing gg","url":"/words-collections/words-containing-gg"},{"name":"words containing awe","url":"/words-collections/words-containing-awe"},{"name":"words containing roy","url":"/words-collections/words-containing-roy"},{"name":"words containing extra","url":"/words-collections/words-containing-extra"},{"name":"words containing whole","url":"/words-collections/words-containing-whole"},{"name":"words containing ion","url":"/words-collections/words-containing-ion"}]},{"categoryName":"Users also visited","links":[{"name":"words containing lin","url":"/words-collections/words-containing-lin"},{"name":"words containing ota","url":"/words-collections/words-containing-ota"},{"name":"words containing syn","url":"/words-collections/words-containing-syn"},{"name":"words containing jab","url":"/words-collections/words-containing-jab"},{"name":"words containing phono","url":"/words-collections/words-containing-phono"},{"name":"words containing thig","url":"/words-collections/words-containing-thig"},{"name":"words containing lea","url":"/words-collections/words-containing-lea"},{"name":"words containing hea","url":"/words-collections/words-containing-hea"},{"name":"words containing ocu","url":"/words-collections/words-containing-ocu"},{"name":"words containing dan","url":"/words-collections/words-containing-dan"},{"name":"words containing volv","url":"/words-collections/words-containing-volv"},{"name":"words containing trau","url":"/words-collections/words-containing-trau"},{"name":"words containing wrap","url":"/words-collections/words-containing-wrap"},{"name":"words containing thor","url":"/words-collections/words-containing-thor"},{"name":"words containing axe","url":"/words-collections/words-containing-axe"},{"name":"words containing eli","url":"/words-collections/words-containing-eli"},{"name":"words containing side","url":"/words-collections/words-containing-side"},{"name":"words containing pp","url":"/words-collections/words-containing-pp"},{"name":"words containing green","url":"/words-collections/words-containing-green"},{"name":"words containing less","url":"/words-collections/words-containing-less"},{"name":"words containing head","url":"/words-collections/words-containing-head"},{"name":"words containing lax","url":"/words-collections/words-containing-lax"},{"name":"words containing self","url":"/words-collections/words-containing-self"},{"name":"words containing ste","url":"/words-collections/words-containing-ste"},{"name":"words containing mob","url":"/words-collections/words-containing-mob"}]},{"categoryName":"Users also visited","links":[{"name":"words containing rea","url":"/words-collections/words-containing-rea"},{"name":"words containing cinc","url":"/words-collections/words-containing-cinc"},{"name":"words containing back","url":"/words-collections/words-containing-back"},{"name":"words containing tor","url":"/words-collections/words-containing-tor"},{"name":"words containing iu","url":"/words-collections/words-containing-iu"},{"name":"words containing eg","url":"/words-collections/words-containing-eg"},{"name":"words containing ohe","url":"/words-collections/words-containing-ohe"},{"name":"words containing x","url":"/words-collections/words-containing-x"},{"name":"words containing onl","url":"/words-collections/words-containing-onl"},{"name":"words containing scien","url":"/words-collections/words-containing-scien"},{"name":"words containing cer","url":"/words-collections/words-containing-cer"},{"name":"words containing ath","url":"/words-collections/words-containing-ath"},{"name":"words containing ent","url":"/words-collections/words-containing-ent"},{"name":"words containing rod","url":"/words-collections/words-containing-rod"},{"name":"words containing men","url":"/words-collections/words-containing-men"},{"name":"words containing ham","url":"/words-collections/words-containing-ham"},{"name":"words containing ref","url":"/words-collections/words-containing-ref"},{"name":"words containing quad","url":"/words-collections/words-containing-quad"},{"name":"words containing non","url":"/words-collections/words-containing-non"},{"name":"words containing for","url":"/words-collections/words-containing-for"},{"name":"words containing eo","url":"/words-collections/words-containing-eo"},{"name":"words containing her","url":"/words-collections/words-containing-her"},{"name":"words containing ador","url":"/words-collections/words-containing-ador"},{"name":"words containing astro","url":"/words-collections/words-containing-astro"},{"name":"words containing sub","url":"/words-collections/words-containing-sub"}]}]},"featureList":[{"feature_heading":"It's completely free.","feature_text":"No fee or subscription is charged for using  'words containing app', and no registration or login is required. There are no limitations to usage. This application is free to use.","fa_class":"../assets/images/star.svg"},{"feature_heading":"Totaly safe","feature_text":"When you use 'words containing app' online tool, the databases that store the information you enter do not save or send it to any other source. Another benefit of using this application is that your data is kept confidential and your work quality is not jeopardised. It is secured and removed from the system by the tool. This allows us to provide comprehensive protection to all of our consumers, ensuring that our product is completely reliable and risk-free to use in any situation, at any time of day or night","fa_class":"../assets/images/star.svg"},{"feature_heading":"Simple to operate","feature_text":"Words containing app is very user-friendly tools. Everything is in one place, so there's no need to think about where to begin. Our online tool is also ad-free, resulting in a superior user experience. The letter can be used to look up your words so that you can complete the online application as directed. These tools are designed to be basic enough for anyone to use.","fa_class":"../assets/images/star.svg"},{"feature_heading":"There are almost no extra resources required.","feature_text":"Words containing app is web-based and works in the cloud. It can be accessed with any device's browser. You are not need to install or download any other tools or software in order to use this application. This tool is extremely user-friendly.","fa_class":"../assets/images/star.svg"},{"feature_heading":"Use without login","feature_text":"Words containing app is absolutely free, and you don't have to give us any personal information like your email address or password to use it. Our service is unrestricted. There is no need to download software or register for a service because the online tool is saved locally in your internet browser.","fa_class":"../assets/images/star.svg"},{"feature_heading":"There are no issues with compatibility.","feature_text":"Words containing app is compatible with all browsers and OS systems. This website's online tool is a web-based service that may be accessed from any computer or mobile device that has access to the internet. Chrome, Safari, Firefox, Microsoft Edge, and a variety of other well-known browsers are all supported. As a result, depending on your preference, you can use this online tool to find the words on a desktop computer, an iPad, a tablet, or a mobile phone. If you use our web service, you will not be needed to purchase or install any additional software or plugins on your computer.","fa_class":"../assets/images/star.svg"}],"faqList":[{"Question":"What is a long word that contain with app?","Answer":" Using this tool, make a list of all L letter words ending with app for word games of all words containing with app for word games, whose length is high. This tools will help you find high-scoring words containing with app."},{"Question":"What is the short words that contain with app?","Answer":"Make all possible words whose length is small.This tools will help you find high-scoring words containing with app."},{"Question":"How to use word containing with app?","Answer":"Make all possible words using this online tools.Enter any letter that the word must start with. All words containing with app are valid words."},{"Question":"If I want to make a complaint about the quality of 'words containing app' , what should I do? ","Answer":"Please contact us with the specifics of the problem you've encountered. A member of our staff will get out to you to assist you with your problem."},{"Question":"Can I use the 'words containing app' on my android device?","Answer":"Yes, you can use in words containing app on an android device easily because they are internet-based tools."},{"Question":"Can I use the 'words containing app' without downloading?","Answer":"Yes, you can use these tools without downloading because they are internet-based tools."},{"Question":"Can I use this tool ( words containing app) in all brouwser ?","Answer":"Yes, you can use this tool in all browser because this is free online utility. this tools are compatible with all browsers and OS system. This tool is a web -based service that may be accessed from any computer or mobile device that has access to the internet. Chrome, Safari, Firefox, Microsoft Edge, and a variety of other well-know browsers are all supported."},{"Question":"How do I communicate if I face any issues or if I want to give any suggestions for 'words containing app' ?","Answer":"If you have any issues using the application 'words containing app' , you can read the FAQ and give suggestions in the contact option and fill in the form."},{"Question":"Do we need to sign up for an account 'words containing app' ?","Answer":"No need to be sign up. Our online tool 'words containing app' is absolutely free, and you don't have to give us any personal information like your email address or password to use it. Our service is unrestricted. There is no need to download software or register for a service because the online tool is saved locally in your internet browser."}]}